feedinlib/__init__.py
feedinlib/cds_request_tools.py
feedinlib/dedup.py
feedinlib/era5.py
feedinlib/models.py
feedinlib/open_FRED.py
feedinlib/powerplants.py
feedinlib-0.1.0rc4.dist-info/LICENSE
feedinlib-0.1.0rc4.dist-info/METADATA
feedinlib-0.1.0rc4.dist-info/WHEEL
feedinlib-0.1.0rc4.dist-info/top_level.txt
feedinlib-0.1.0rc4.dist-info/RECORD
