Metadata-Version: 2.1
Name: feedinlib
Version: 0.1.0rc4
Summary: Creating time series from pv or wind power plants.
Home-page: http://github.com/oemof/feedinlib
Author: oemof developer group
Author-email: windpowerlib@rl-institut.de
License: MIT
Platform: UNKNOWN
Requires-Dist: cdsapi (>=0.1.4)
Requires-Dist: geopandas
Requires-Dist: numpy (>=1.7.0)
Requires-Dist: oedialect (>=0.0.6.dev0)
Requires-Dist: open-FRED-cli
Requires-Dist: pandas (>=0.13.1)
Requires-Dist: pvlib (>=0.7.0)
Requires-Dist: tables
Requires-Dist: windpowerlib (>=0.2.0)
Requires-Dist: xarray (>=0.12.0)
Requires-Dist: descartes
Provides-Extra: dev
Requires-Dist: jupyter ; extra == 'dev'
Requires-Dist: nbformat ; extra == 'dev'
Requires-Dist: punch.py ; extra == 'dev'
Requires-Dist: pytest ; extra == 'dev'
Requires-Dist: sphinx-rtd-theme ; extra == 'dev'
Provides-Extra: examples
Requires-Dist: jupyter ; extra == 'examples'
Requires-Dist: matplotlib ; extra == 'examples'
Requires-Dist: descartes ; extra == 'examples'
